[
    {
        "profileFor": "myself",
        "name": "Arjun Kumar",
        "email": "arjun.kumar@example.com",
        "password": "hashed_password_1",
        "gender": "male",
        "DOB": "1990-03-15",
        "subCaste": "Rajput",
        "motherTongue": "Hindi",
        "maritalStatus": "Single",
        "country": "India",
        "city": "Jaipur",
        "state": "Rajasthan",
        "height": "5'10\"",
        "education": "Bachelor's Degree",
        "occupation": "Engineer",
        "income": 500000,
        "physicalStatus": "Fit",
        "familyStatus": "middle",
        "familyType": "Nuclear",
        "about": "I am an engineer working in a reputed firm.",
        "star": "Ashwini",
        "raasi": "Mesha (Aries)",
        "gothra": "Bharadwaja",
        "chevvaiDosham": "NO"
        },
    {
        "profileFor": "son",
        "name": "Vikram Singh",
        "email": "vikram.singh@example.com",
        "password": "hashed_password_2",
        "gender": "male",
        "DOB": "1992-07-10",
        "subCaste": "Rajput",
        "motherTongue": "Punjabi",
        "maritalStatus": "Single",
        "country": "India",
        "city": "Ludhiana",
        "state": "Punjab",
        "height": "5'8\"",
        "education": "Master's Degree",
        "occupation": "Teacher",
        "income": 400000,
        "physicalStatus": "Fit",
        "familyStatus": "middle",
        "familyType": "Joint",
        "about": "Passionate about teaching and helping students.",
        "star": "Ashwini",
        "raasi": "Vrishabha (Taurus)",
        "gothra": "Kashyapa",
        "chevvaiDosham": "NO"
        },
    {
        "profileFor": "myself",
        "name": "Rohan Verma",
        "email": "rohan.verma@example.com",
        "password": "hashed_password_3",
        "gender": "male",
        "DOB": "1988-11-25",
        "subCaste": "Rajput",
        "motherTongue": "Gujarati",
        "maritalStatus": "Single",
        "country": "India",
        "city": "Ahmedabad",
        "state": "Gujarat",
        "height": "5'9\"",
        "education": "Bachelor's Degree",
        "occupation": "Architect",
        "income": 600000,
        "physicalStatus": "Fit",
        "familyStatus": "high",
        "familyType": "Nuclear",
        "about": "Architect with a love for design and innovation.",
        "star": "Ashwini",
        "raasi": "Tula (Libra)",
        "gothra": "Vasishta",
        "chevvaiDosham": "YES"
        },
    {
        "profileFor": "brother",
        "name": "Aman Mehta",
        "email": "aman.mehta@example.com",
        "password": "hashed_password_4",
        "gender": "male",
        "DOB": "1995-05-05",
        "subCaste": "Rajput",
        "motherTongue": "Hindi",
        "maritalStatus": "Single",
        "country": "India",
        "city": "New Delhi",
        "state": "Delhi",
        "height": "5'7\"",
        "education": "Associate Degree",
        "occupation": "Mechanic",
        "income": 350000,
        "physicalStatus": "Average",
        "familyStatus": "middle",
        "familyType": "Joint",
        "about": "Mechanic with a passion for cars and bikes.",
        "star": "Ashwini",
        "raasi": "Simha (Leo)",
        "gothra": "Agastya",
        "chevvaiDosham": "NO"
        },
    {
        "profileFor": "myself",
        "name": "Suresh Rao",
        "email": "suresh.rao@example.com",
        "password": "hashed_password_5",
        "gender": "male",
        "DOB": "1986-02-28",
        "subCaste": "Rajput",
        "motherTongue": "Telugu",
        "maritalStatus": "Divorced",
        "country": "India",
        "city": "Hyderabad",
        "state": "Telangana",
        "height": "6'0\"",
        "education": "Doctorate",
        "occupation": "Professor",
        "income": 700000,
        "physicalStatus": "Fit",
        "familyStatus": "high",
        "familyType": "Nuclear",
        "about": "Professor with a deep love for knowledge.",
        "star": "Ashwini",
        "raasi": "Vrischika (Scorpio)",
        "gothra": "Pulaha",
        "chevvaiDosham": "Don't Know"
        },
    {
        "profileFor": "friend",
        "name": "Karan Patel",
        "email": "karan.patel@example.com",
        "password": "hashed_password_6",
        "gender": "male",
        "DOB": "1994-04-20",
        "subCaste": "Rajput",
        "motherTongue": "Gujarati",
        "maritalStatus": "Single",
        "country": "India",
        "city": "Surat",
        "state": "Gujarat",
        "height": "5'11\"",
        "education": "Bachelor's Degree",
        "occupation": "Software Developer",
        "income": 800000,
        "physicalStatus": "Fit",
        "familyStatus": "high",
        "familyType": "Nuclear",
        "about": "Software developer with a love for coding.",
        "star": "Ashwini",
        "raasi": "Simha (Leo)",
        "gothra": "Kratu",
        "chevvaiDosham": "NO"
        },
    {
        "profileFor": "son",
        "name": "Rahul Sharma",
        "email": "rahul.sharma@example.com",
        "password": "hashed_password_7",
        "gender": "male",
        "DOB": "1987-09-09",
        "subCaste": "Rajput",
        "motherTongue": "Hindi",
        "maritalStatus": "Married",
        "country": "India",
        "city": "Mumbai",
        "state": "Maharashtra",
        "height": "5'6\"",
        "education": "Master's Degree",
        "occupation": "Manager",
        "income": 900000,
        "physicalStatus": "Average",
        "familyStatus": "middle",
        "familyType": "Joint",
        "about": "Manager in a multinational company.",
        "star": "Ashwini",
        "raasi": "Kanya (Virgo)",
        "gothra": "Parasara",
        "chevvaiDosham": "YES"
        },
    {
        "profileFor": "myself",
        "name": "Deepak Gupta",
        "email": "deepak.gupta@example.com",
        "password": "hashed_password_8",
        "gender": "male",
        "DOB": "1993-12-12",
        "subCaste": "Rajput",
        "motherTongue": "Hindi",
        "maritalStatus": "Single",
        "country": "India",
        "city": "Pune",
        "state": "Maharashtra",
        "height": "5'10\"",
        "education": "Bachelor's Degree",
        "occupation": "Civil Engineer",
        "income": 650000,
        "physicalStatus": "Fit",
        "familyStatus": "middle",
        "familyType": "Nuclear",
        "about": "Civil engineer with a focus on sustainability.",
        "star": "Ashwini",
        "raasi": "Vrischika (Scorpio)",
        "gothra": "Vamadeva",
        "chevvaiDosham": "Don't Know"
        },
    {
        "profileFor": "brother",
        "name": "Manoj Yadav",
        "email": "manoj.yadav@example.com",
        "password": "hashed_password_9",
        "gender": "male",
        "DOB": "1989-06-18",
        "subCaste": "Rajput",
        "motherTongue": "Hindi",
        "maritalStatus": "Single",
        "country": "India",
        "city": "Lucknow",
        "state": "Uttar Pradesh",
        "height": "5'8\"",
        "education": "Bachelor's Degree",
        "occupation": "Businessman",
        "income": 550000,
        "physicalStatus": "Average",
        "familyStatus": "middle",
        "familyType": "Joint",
        "about": "Businessman running a family-owned store.",
        "star": "Ashwini",
        "raasi": "Dhanu (Sagittarius)",
        "gothra": "Atri",
        "chevvaiDosham": "NO"
        },
    {
        "profileFor": "myself",
        "name": "Ravi Chauhan",
        "email": "ravi.chauhan@example.com",
        "password": "hashed_password_10",
        "gender": "male",
        "DOB": "1991-01-01",
        "subCaste": "Rajput",
        "motherTongue": "Hindi",
        "maritalStatus": "Single",
        "country": "India",
        "city": "Patna",
        "state": "Bihar",
        "height": "5'7\"",
        "education": "Master's Degree",
        "occupation": "Consultant",
        "income": 700000,
        "physicalStatus": "Fit",
        "familyStatus": "high",
        "familyType": "Nuclear",
        "about": "Consultant in a leading firm.",
        "star":  "Ashwini",
        "raasi": "Meena (Pisces)",
        "gothra": "Angiras",
        "chevvaiDosham": "Don't Know"

    },
    {
        "profileFor": "myself",
        "name": "Priya Sharma",
        "email": "priya.sharma@example.com",
        "password": "hashed_password_11",
        "gender": "female",
        "DOB": "1994-04-12",
        "subCaste": "Rajput",
        "motherTongue": "Hindi",
        "maritalStatus": "Single",
        "country": "India",
        "city": "Jaipur",
        "state": "Rajasthan",
        "height": "5'5\"",
        "education": "Master's Degree",
        "occupation": "Teacher",
        "income": 400000,
        "physicalStatus": "Fit",
        "familyStatus": "middle",
        "familyType": "Nuclear",
        "about": "Teacher with a passion for literature.",
        "star": "Ashwini",
        "raasi": "Meena (Pisces)",
        "gothra": "Bharadwaja",
        "chevvaiDosham": "NO"
    },
    {
        "profileFor": "daughter",
        "name": "Aishwarya Iyer",
        "email": "aishwarya.iyer@example.com",
        "password": "hashed_password_12",
        "gender": "female",
        "DOB": "1996-08-22",
        "subCaste": "Rajput",
        "motherTongue": "Tamil",
        "maritalStatus": "Single",
        "country": "India",
        "city": "Chennai",
        "state": "Tamil Nadu",
        "height": "5'4\"",
        "education": "Bachelor's Degree",
        "occupation": "Software Engineer",
        "income": 600000,
        "physicalStatus": "Fit",
        "familyStatus": "high",
        "familyType": "Nuclear",
        "about": "Software engineer with a love for technology.",
        "star": "Ashwini",
        "raasi": "Mesha (Aries)",
        "gothra": "Kashyapa",
        "chevvaiDosham": "NO"
    },
    {
        "profileFor": "myself",
        "name": "Neha Agarwal",
        "email": "neha.agarwal@example.com",
        "password": "hashed_password_13",
        "gender": "female",
        "DOB": "1992-05-03",
        "subCaste": "Rajput",
        "motherTongue": "Hindi",
        "maritalStatus": "Single",
        "country": "India",
        "city": "Mumbai",
        "state": "Maharashtra",
        "height": "5'3\"",
        "education": "MBA",
        "occupation": "Marketing Manager",
        "income": 800000,
        "physicalStatus": "Fit",
        "familyStatus": "high",
        "familyType": "Joint",
        "about": "Marketing manager with an MBA degree.",
        "star":  "Ashwini",
        "raasi": "Kanya (Virgo)",
        "gothra": "Vasishta",
        "chevvaiDosham": "YES"
    },
    {
        "profileFor": "sister",
        "name": "Sneha Joshi",
        "email": "sneha.joshi@example.com",
        "password": "hashed_password_14",
        "gender": "female",
        "DOB": "1989-02-18",
        "subCaste": "Rajput",
        "motherTongue": "Marathi",
        "maritalStatus": "Single",
        "country": "India",
        "city": "Pune",
        "state": "Maharashtra",
        "height": "5'2\"",
        "education": "Bachelor's Degree",
        "occupation": "Nurse",
        "income": 300000,
        "physicalStatus": "Average",
        "familyStatus": "middle",
        "familyType": "Nuclear",
        "about": "Nurse working in a leading hospital.",
        "star": "Ashwini",
        "raasi": "Kanya (Virgo)",
        "gothra": "Angiras",
        "chevvaiDosham": "NO"
    },
    {
        "profileFor": "myself",
        "name": "Riya Desai",
        "email": "riya.desai@example.com",
        "password": "hashed_password_15",
        "gender": "female",
        "DOB": "1990-11-30",
        "subCaste": "Rajput",
        "motherTongue": "Gujarati",
        "maritalStatus": "Divorced",
        "country": "India",
        "city": "Ahmedabad",
        "state": "Gujarat",
        "height": "5'6\"",
        "education": "Doctorate",
        "occupation": "Professor",
        "income": 700000,
        "physicalStatus": "Fit",
        "familyStatus": "high",
        "familyType": "Nuclear",
        "about": "Professor with a passion for teaching.",
        "star":"Ashwini",
        "raasi": "Vrishabha (Taurus)",
        "gothra": "Pulaha",
        "chevvaiDosham": "Don't Know"
    },
    {
        "profileFor": "daughter",
        "name": "Anjali Nair",
        "email": "anjali.nair@example.com",
        "password": "hashed_password_16",
        "gender": "female",
        "DOB": "1995-10-14",
        "subCaste": "Rajput",
        "motherTongue": "Malayalam",
        "maritalStatus": "Single",
        "country": "India",
        "city": "Kochi",
        "state": "Kerala",
        "height": "5'5\"",
        "education": "Bachelor's Degree",
        "occupation": "Civil Engineer",
        "income": 500000,
        "physicalStatus": "Fit",
        "familyStatus": "middle",
        "familyType": "Nuclear",
        "about": "Civil engineer focused on green buildings.",
        "star": "Ashwini",
        "raasi": "Karka (Cancer)",
        "gothra": "Atri",
        "chevvaiDosham": "NO"
    },
    {
        "profileFor": "myself",
        "name": "Pooja Patil",
        "email": "pooja.patil@example.com",
        "password": "hashed_password_17",
        "gender": "female",
        "DOB": "1993-06-25",
        "subCaste": "Rajput",
        "motherTongue": "Marathi",
        "maritalStatus": "Single",
        "country": "India",
        "city": "Mumbai",
        "state": "Maharashtra",
        "height": "5'3\"",
        "education": "Bachelor's Degree",
        "occupation": "Graphic Designer",
        "income": 450000,
        "physicalStatus": "Fit",
        "familyStatus": "middle",
        "familyType": "Nuclear",
        "about": "Creative graphic designer.",
        "star": "Ashwini",
        "raasi": "Vrishchika (Scorpio)",
        "gothra": "Kashyapa",
        "chevvaiDosham": "YES"
    }
]
